sparse_ir/__init__.py
sparse_ir/_gauss.py
sparse_ir/_util.py
sparse_ir/abstract.py
sparse_ir/augment.py
sparse_ir/basis.py
sparse_ir/basis_set.py
sparse_ir/dlr.py
sparse_ir/kernel.py
sparse_ir/poly.py
sparse_ir/sampling.py
sparse_ir/sve.py
sparse_ir-2.1.1.dist-info/licenses/LICENSE.txt
sparse_ir-2.1.1.dist-info/METADATA
sparse_ir-2.1.1.dist-info/WHEEL
sparse_ir-2.1.1.dist-info/top_level.txt
sparse_ir-2.1.1.dist-info/RECORD
