Metadata-Version: 2.4
Name: sparse-ir
Version: 2.1.1
Summary: Python bindings for the libsparseir library, providing efficient sparse intermediate representation for many-body physics calculations
Author: SpM-lab
License-Expression: MIT
Project-URL: Homepage, https://github.com/SpM-lab/sparse-r
Project-URL: Repository, https://github.com/SpM-lab/sparse-r
Project-URL: Bug Tracker, https://github.com/SpM-lab/sparse-r/issues
Keywords: physics,many-body,green-functions,sparse-ir
Classifier: Development Status :: 5 - Production/Stable
Classifier: Intended Audience :: Science/Research
Classifier: Programming Language :: Python :: 3
Classifier: Programming Language :: Python :: 3.12
Classifier: Topic :: Scientific/Engineering :: Physics
Requires-Python: >=3.10
License-File: LICENSE.txt
Requires-Dist: numpy
Requires-Dist: scipy
Requires-Dist: pylibsparseir<0.9.0,>=0.8.0
Dynamic: license-file
